dash_dvx/DashDvx.py
dash_dvx/Filterbuilder.py
dash_dvx/Grid.py
dash_dvx/List.py
dash_dvx/__init__.py
dash_dvx/_imports_.py
dash_dvx/dash_dvx.min.js
dash_dvx/dash_dvx.min.js.map
dash_dvx/metadata.json
dash_dvx/package-info.json
dash_dvx-1.3.1.dist-info/LICENSE
dash_dvx-1.3.1.dist-info/METADATA
dash_dvx-1.3.1.dist-info/WHEEL
dash_dvx-1.3.1.dist-info/top_level.txt
dash_dvx-1.3.1.dist-info/RECORD
