Metadata-Version: 2.1
Name: dash-dvx
Version: 1.3.1
Summary: A simple wrapper for the Devextreme js library of components
Home-page: https://github.com/azur-scd/dash_dvx
Author: Géraldine Geoffroy
Author-email: geraldine.geoffroy@univ-cotedazur.fr
License: MIT
Platform: UNKNOWN
Classifier: Framework :: Dash
